mosaygent/__init__.py
mosaygent/command_runner.py
mosaygent/logger.py
mosaygent/middleware.py
mosaygent/routes/__init__.py
mosaygent/routes/environment.py
mosaygent/routes/firebase.py
mosaygent/routes/flutter.py
mosaygent/routes/github.py
mosaygent/routes/supabase.py
mosaygent/services/__init__.py
mosaygent/services/cloudrun.py
mosaygent/services/environment.py
mosaygent/services/flutter.py
mosaygent/services/firebase/__init__.py
mosaygent/services/firebase/auth.py
mosaygent/services/firebase/config.py
mosaygent/services/firebase/deploy.py
mosaygent/services/firebase/functions.py
mosaygent/services/firebase/project.py
mosaygent-0.1.2.dist-info/METADATA
mosaygent-0.1.2.dist-info/WHEEL
mosaygent-0.1.2.dist-info/RECORD
