Metadata-Version: 2.4
Name: mosaygent
Version: 0.1.2
Summary: A locally running API for powering the Mosayic tool
Author-email: John Kealy <john@kealy.studio>
License: MIT
Requires-Python: <3.13,>=3.10
Requires-Dist: fastapi>=0.119.0
Requires-Dist: firebase-admin>=7.1.0
Requires-Dist: httpx>=0.28.1
Requires-Dist: jinja2>=3.1.6
Requires-Dist: mosayic>=0.0.1
Requires-Dist: psutil>=6.1.1
Requires-Dist: pydantic-settings>=2.11.0
Requires-Dist: pydantic>=2.12.3
Requires-Dist: pytest-asyncio>=1.2.0
Requires-Dist: pytest-cov>=6.0.0
Requires-Dist: pytest-mock>=3.14.0
Requires-Dist: pytest>=8.4.2
Requires-Dist: python-multipart>=0.0.20
Requires-Dist: pyyaml>=6.0.1
Requires-Dist: requests>=2.32.5
Requires-Dist: resend>=2.17.0
Requires-Dist: supabase>=2.22.0
Requires-Dist: uvicorn>=0.37.0
